README.md
setup.py
lib/__init__.py
lib/tests.py
lib/version.py
lib/check/__init__.py
lib/check/checkSelenium.py
libseleniumagent/__init__.py
libseleniumagent/base.py
libseleniumagent/version.py
libseleniumagent.egg-info/PKG-INFO
libseleniumagent.egg-info/SOURCES.txt
libseleniumagent.egg-info/dependency_links.txt
libseleniumagent.egg-info/requires.txt
libseleniumagent.egg-info/top_level.txt