Metadata-Version: 2.1
Name: libseleniumagent
Version: 1.0.0
Summary: Library for building Infrasonar selenium agents
Home-page: https://github.com/infrasonar/selenium-agent
Download-URL: https://github.com/infrasonar/selenium-agent/tarball/v1.0.0
Author: Cesbit
Author-email: info@cesbit.com
Keywords: monitoring,infrasonar,agent,selenium
Classifier: Intended Audience :: Developers
Classifier: Operating System :: OS Independent
Classifier: Programming Language :: Python :: 3.9
Classifier: Programming Language :: Python :: 3.10
Classifier: Programming Language :: Python :: 3.11
Classifier: Programming Language :: Python :: 3.12
Classifier: Programming Language :: Python :: 3 :: Only
Classifier: Topic :: Software Development :: Libraries :: Python Modules
Classifier: Topic :: Text Processing :: Linguistic
Requires-Dist: selenium
